package_example/__init__.py
package_example/example_class.py
ipptemplate-0.1.22.dist-info/LICENSE.txt
ipptemplate-0.1.22.dist-info/METADATA
ipptemplate-0.1.22.dist-info/WHEEL
ipptemplate-0.1.22.dist-info/top_level.txt
ipptemplate-0.1.22.dist-info/RECORD
