Metadata-Version: 2.1
Name: ipptemplate
Version: 0.1.22
Summary: A template package from iPP eng. GmbH
Home-page: https://github.com/ipp-git/python_template
Author: iPP (Thierry Lochmatter)
Author-email: info@ipp.swiss
License: Proprietary license
Project-URL: Homepage, https://ipp.swiss
Project-URL: Download, https://pypi.org/project/ipptemplate
Project-URL: Source Code, https://github.com/ipp-git/python_template
Project-URL: Bug Tracker, https://github.com/ipp-git/python_template/issues
Keywords: iPP,application
Platform: UNKNOWN
Classifier: Development Status :: 1 - Planning
Classifier: Intended Audience :: Science/Research
Classifier: Intended Audience :: Developers
Classifier: Programming Language :: Python :: 3
Classifier: Operating System :: Microsoft :: Windows
Classifier: Topic :: Software Development
Classifier: Topic :: Scientific/Engineering
Requires-Python: >=3.9
License-File: LICENSE.txt
